[
  {
    "model": "mad_api.event",
    "pk": 1,
    "fields": {
      "uid": 1,
      "title": "A day with the Cats",
      "description": "These are some of the many funny poses that my cats do when just lying around the house",
      "location": "Home",
      "lat": 36.200456,
      "long": -86.754647,
      "city": "Nashville, TN",
      "date": "2022-12-20",
      "daytime": 2,
      "category": 12,
      "rating": 80,
      "public": true
    }
  },
  {
    "model": "mad_api.event",
    "pk": 2,
    "fields": {
      "uid": 1,
      "title": "Birthday Dinner",
      "description": "Went to Sean Brock's old place to see if it's still worth it",
      "location": "Husk Nashville",
      "lat": 36.155393,
      "long": -86.769677,
      "city": "Nashville, TN",
      "date": "2022-01-09",
      "daytime": 5,
      "category": 4,
      "rating": 95,
      "public": true
    }
  },
  {
    "model": "mad_api.event",
    "pk": 3,
    "fields": {
      "uid": 1,
      "title": "The sights of New York City",
      "description": "Spent the day walking around NYC, figured I's share some pics of the places I saw",
      "location": "Husk Nashville",
      "lat": 40.748426,
      "long": -73.984576,
      "city": "New York, NY",
      "date": "2022-07-12",
      "daytime": 2,
      "category": 11,
      "rating": 75,
      "public": true
    }
  },
  {
    "model": "mad_api.event",
    "pk": 4,
    "fields": {
      "uid": 1,
      "title": "Hanging with The Boys",
      "description": "Some early night bar hangs with my dudes.  Beer, Foozeball, Pool, and good times",
      "location": "Melrose Billiard Hall",
      "lat": 36.122007,
      "long": -86.775526,
      "city": "Nashville, TN",
      "date": "2022-10-15",
      "daytime": 4,
      "category": 2,
      "rating": 100,
      "public": true
    }
  }
]
